CHANGES.rst
MANIFEST.in
README.rst
TODO.rst
setup.cfg
setup.py
archiveIO/__init__.py
archiveIO/tests.py
archiveIO.egg-info/PKG-INFO
archiveIO.egg-info/SOURCES.txt
archiveIO.egg-info/dependency_links.txt
archiveIO.egg-info/requires.txt
archiveIO.egg-info/top_level.txt
archiveIO.egg-info/zip-safe