Metadata-Version: 1.0
Name: archiveIO
Version: 0.4.3
Summary: Convenience decorators for reading and writing to compressed archives
Home-page: https://github.com/invisibleroads/archiveIO
Author: Roy Hyunjin Han
Author-email: starsareblueandfaraway@gmail.com
License: MIT
Keywords: zip tar.gz tar.bz2 tar
Platform: UNKNOWN
Classifier: Intended Audience :: Developers
Classifier: Programming Language :: Python
Classifier: License :: OSI Approved :: MIT License
